{
  "status": "ok",
  "timestamp": "2026-02-26T18:04:27.235022+00:00",
  "fetched_candidates": 50,
  "unseen_candidates": 45,
  "blocked_domain_candidates": 3,
  "selected_candidates": 1,
  "generated_posts": [
    {
      "title": "Trace raises $3M to solve the AI agent adoption problem in enterprise — Practical Automation Insight",
      "link": "auto/20260226-trace-raises-3m-to-solve-the-ai-agent-adoption-problem-in-en-1d970b47.html",
      "score": 83.9814,
      "source": "TechCrunch"
    }
  ],
  "skipped": [],
  "source_failures": [],
  "dry_run": false,
  "min_score": 34.0,
  "min_summary_length": 120,
  "min_description_length": 140,
  "min_keyword_hits": 2,
  "allowed_domains": [
    "azure.microsoft.com",
    "github.blog",
    "theverge.com",
    "techcrunch.com"
  ],
  "max_posts": 1
}
